odoo/addons/purchase_order_no_price/README.rst
odoo/addons/purchase_order_no_price/__init__.py
odoo/addons/purchase_order_no_price/__manifest__.py
odoo/addons/purchase_order_no_price/i18n/es.po
odoo/addons/purchase_order_no_price/models/__init__.py
odoo/addons/purchase_order_no_price/models/purchase_order_line.py
odoo/addons/purchase_order_no_price/models/res_partner.py
odoo/addons/purchase_order_no_price/readme/CONFIGURE.md
odoo/addons/purchase_order_no_price/readme/CONTRIBUTORS.md
odoo/addons/purchase_order_no_price/readme/DESCRIPTION.md
odoo/addons/purchase_order_no_price/readme/USAGE.md
odoo/addons/purchase_order_no_price/static/description/icon.png
odoo/addons/purchase_order_no_price/static/description/index.html
odoo/addons/purchase_order_no_price/tests/__init__.py
odoo/addons/purchase_order_no_price/tests/test_purchase_order_no_price.py
odoo/addons/purchase_order_no_price/views/res_partner_views.xml
odoo_addon_purchase_order_no_price-17.0.1.0.0.1.dist-info/METADATA
odoo_addon_purchase_order_no_price-17.0.1.0.0.1.dist-info/WHEEL
odoo_addon_purchase_order_no_price-17.0.1.0.0.1.dist-info/top_level.txt
odoo_addon_purchase_order_no_price-17.0.1.0.0.1.dist-info/RECORD
